{
    "nakup": {
        "AUD": "18,40",
        "CAD": "18,30",
        "CHF": "24,30",
        "DKK": "3,59",
        "EUR": "26,50",
        "GBP": "29,70",
        "HRK": "3,50",
        "HUF": "8,75",
        "JPY": "23,30",
        "NOK": "2,97",
        "PLN": "6,15",
        "RUB": "33,00",
        "SEK": "2,74",
        "USD": "24,20"
    },
    "nakupVIP": {
        "AUD": "18,700",
        "CAD": "18,600",
        "CHF": "24,600",
        "DKK": "3,610",
        "EUR": "26,800",
        "GBP": "30,000",
        "HRK": "3,560",
        "HUF": "8,800",
        "JPY": "23,600",
        "NOK": "2,990",
        "PLN": "6,200",
        "RUB": "35,000",
        "SEK": "2,760",
        "USD": "24,400"
    },
    "nasobek": {
        "AUD": "1",
        "CAD": "1",
        "CHF": "1",
        "DKK": "1",
        "EUR": "1",
        "GBP": "1",
        "HRK": "1",
        "HUF": "100",
        "JPY": "100",
        "NOK": "1",
        "PLN": "1",
        "RUB": "100",
        "SEK": "1",
        "USD": "1"
    },
    "prodej": {
        "AUD": "19,10",
        "CAD": "19,00",
        "CHF": "25,00",
        "DKK": "3,66",
        "EUR": "27,20",
        "GBP": "30,50",
        "HRK": "3,70",
        "HUF": "9,05",
        "JPY": "24,10",
        "NOK": "3,04",
        "PLN": "6,40",
        "RUB": "41,00",
        "SEK": "2,81",
        "USD": "24,80"
    },
    "prodejVIP": {
        "AUD": "19,000",
        "CAD": "18,900",
        "CHF": "24,900",
        "DKK": "3,650",
        "EUR": "27,100",
        "GBP": "30,400",
        "HRK": "3,660",
        "HUF": "9,000",
        "JPY": "24,000",
        "NOK": "3,030",
        "PLN": "6,350",
        "RUB": "40,000",
        "SEK": "2,800",
        "USD": "24,700"
    }
}