{
    "nakup": {
        "AUD": "15,40",
        "CAD": "16,80",
        "CHF": "22,20",
        "DKK": "3,41",
        "EUR": "25,30",
        "GBP": "28,80",
        "HRK": "3,35",
        "HUF": "7,80",
        "JPY": "19,30",
        "NOK": "2,67",
        "PLN": "5,90",
        "RUB": "30,00",
        "SEK": "2,42",
        "USD": "22,00"
    },
    "nakupVIP": {
        "AUD": "15,700",
        "CAD": "17,100",
        "CHF": "22,400",
        "DKK": "3,430",
        "EUR": "25,600",
        "GBP": "29,100",
        "HRK": "3,400",
        "HUF": "7,850",
        "JPY": "19,600",
        "NOK": "2,690",
        "PLN": "5,950",
        "RUB": "31,000",
        "SEK": "2,440",
        "USD": "22,300"
    },
    "nasobek": {
        "AUD": "1",
        "CAD": "1",
        "CHF": "1",
        "DKK": "1",
        "EUR": "1",
        "GBP": "1",
        "HRK": "1",
        "HUF": "100",
        "JPY": "100",
        "NOK": "1",
        "PLN": "1",
        "RUB": "100",
        "SEK": "1",
        "USD": "1"
    },
    "prodej": {
        "AUD": "16,10",
        "CAD": "17,50",
        "CHF": "22,80",
        "DKK": "3,50",
        "EUR": "26,00",
        "GBP": "29,60",
        "HRK": "3,60",
        "HUF": "8,10",
        "JPY": "20,10",
        "NOK": "2,75",
        "PLN": "6,15",
        "RUB": "37,00",
        "SEK": "2,50",
        "USD": "22,70"
    },
    "prodejVIP": {
        "AUD": "16,000",
        "CAD": "17,400",
        "CHF": "22,700",
        "DKK": "3,480",
        "EUR": "25,900",
        "GBP": "29,500",
        "HRK": "3,550",
        "HUF": "8,050",
        "JPY": "20,000",
        "NOK": "2,740",
        "PLN": "6,100",
        "RUB": "36,000",
        "SEK": "2,490",
        "USD": "22,600"
    }
}