{
    "nakup": {
        "AUD": "16,00",
        "CAD": "16,40",
        "CHF": "21,70",
        "DKK": "3,39",
        "EUR": "25,20",
        "GBP": "28,00",
        "HRK": "3,40",
        "HUF": "7,90",
        "JPY": "19,30",
        "NOK": "2,64",
        "PLN": "5,90",
        "RUB": "31,00",
        "SEK": "2,43",
        "USD": "21,60"
    },
    "nakupVIP": {
        "AUD": "16,200",
        "CAD": "16,700",
        "CHF": "22,000",
        "DKK": "3,410",
        "EUR": "25,400",
        "GBP": "28,300",
        "HRK": "3,420",
        "HUF": "7,950",
        "JPY": "19,600",
        "NOK": "2,660",
        "PLN": "5,950",
        "RUB": "32,000",
        "SEK": "2,450",
        "USD": "21,900"
    },
    "nasobek": {
        "AUD": "1",
        "CAD": "1",
        "CHF": "1",
        "DKK": "1",
        "EUR": "1",
        "GBP": "1",
        "HRK": "1",
        "HUF": "100",
        "JPY": "100",
        "NOK": "1",
        "PLN": "1",
        "RUB": "100",
        "SEK": "1",
        "USD": "1"
    },
    "prodej": {
        "AUD": "16,60",
        "CAD": "17,10",
        "CHF": "22,40",
        "DKK": "3,47",
        "EUR": "25,80",
        "GBP": "28,80",
        "HRK": "3,63",
        "HUF": "8,20",
        "JPY": "20,10",
        "NOK": "2,72",
        "PLN": "6,15",
        "RUB": "38,00",
        "SEK": "2,51",
        "USD": "22,30"
    },
    "prodejVIP": {
        "AUD": "16,500",
        "CAD": "17,000",
        "CHF": "22,300",
        "DKK": "3,460",
        "EUR": "25,700",
        "GBP": "28,700",
        "HRK": "3,580",
        "HUF": "8,150",
        "JPY": "20,000",
        "NOK": "2,710",
        "PLN": "6,100",
        "RUB": "37,000",
        "SEK": "2,500",
        "USD": "22,200"
    }
}